packageversion/__init__.py
packageversion/packageversion.py
packageversion-1.0.2.dist-info/DESCRIPTION.rst
packageversion-1.0.2.dist-info/METADATA
packageversion-1.0.2.dist-info/RECORD
packageversion-1.0.2.dist-info/WHEEL
packageversion-1.0.2.dist-info/metadata.json
packageversion-1.0.2.dist-info/top_level.txt
tests/__init__.py
tests/test_packageversion.py
