Metadata-Version: 2.0
Name: packageversion
Version: 1.0.2
Summary: Library to generate python package version for CI
Home-page: https://github.com/Yuav/python-packageversion
Author: Jon Skarpeteig
Author-email: jon.skarpeteig@gmail.com
License: UNKNOWN
Platform: UNKNOWN
Classifier: License :: OSI Approved :: Apache Software License
Classifier: Operating System :: OS Independent
Classifier: Programming Language :: Python :: 3.2
Classifier: Programming Language :: Python :: 3.3
Classifier: Programming Language :: Python :: 3.4
Requires-Dist: flexmock
Requires-Dist: semantic-version
